pazer_core_python/CoreConfig.py
pazer_core_python/__init__.py
test/__init__.py
pazer_core_python-0.4.1.dist-info/LICENSE
pazer_core_python-0.4.1.dist-info/METADATA
pazer_core_python-0.4.1.dist-info/WHEEL
pazer_core_python-0.4.1.dist-info/top_level.txt
pazer_core_python-0.4.1.dist-info/RECORD
