Metadata-Version: 2.1
Name: pazer_core_python
Version: 0.4.1
Summary: Pazer Core - Python
Author: David Kim
Author-email: David Kim <woody@woody.co.kr>
Project-URL: Homepage, https://github.com/pazer-app/pazer_core_python
Project-URL: Bug Tracker, https://github.com/pazer-app/pazer_core_python/issues
Keywords: pazer,core
Classifier: Programming Language :: Python :: 3
Classifier: License :: OSI Approved :: MIT License
Classifier: Operating System :: OS Independent
Requires-Python: >=3.7
License-File: LICENSE
Requires-Dist: pazer_database_python>=0.4.1
Requires-Dist: pazer_logger_python>=0.4.1
Requires-Dist: fastapi>=0.115.6
Requires-Dist: pydantic>=2.10.4
